git_viewer/__init__.py
git_viewer/__main__.py
git_viewer/api_commands.py
git_viewer/api_subprocess.py
git_viewer/check.py
git_viewer/color_decoder.py
git_viewer/commands.py
git_viewer/constants.py
git_viewer/diff.py
git_viewer/log.py
git_viewer/main.py
git_viewer/model.py
git_viewer/model_hints.py
git_viewer/model_input_history.py
git_viewer/settings.py
git_viewer/show.py
git_viewer/string_formatter.py
git_viewer/urwid_color_encoder.py
git_viewer/urwid_constants.py
git_viewer/urwid_edit_with_history.py
git_viewer/urwid_text_layout.py
git_viewer/utils.py
git_viewer/doc/command_template.py
git_viewer/doc/complete.bash
git_viewer/doc/intro.md
git_viewer/doc/version.txt
git_viewer-1.25.0.dist-info/licenses/LICENSE
git_viewer-1.25.0.dist-info/METADATA
git_viewer-1.25.0.dist-info/WHEEL
git_viewer-1.25.0.dist-info/entry_points.txt
git_viewer-1.25.0.dist-info/top_level.txt
git_viewer-1.25.0.dist-info/RECORD
