Metadata-Version: 2.4
Name: git-viewer
Version: 1.25.0
Summary: An interactive git viewer based on urwid. Similar to gitk but in a terminal.
Home-page: https://gitlab.com/erzo/git-viewer
Author: erzo
Author-email: erzo@posteo.de
Project-URL: Bug Tracker, https://gitlab.com/erzo/git-viewer/-/issues
Classifier: Programming Language :: Python :: 3
Classifier: License :: OSI Approved :: BSD License
Classifier: Operating System :: POSIX
Classifier: Operating System :: Unix
Classifier: Operating System :: MacOS :: MacOS X
Classifier: Topic :: Software Development :: Version Control :: Git
Classifier: Environment :: Console
Requires-Python: >=3.5
License-File: LICENSE
Requires-Dist: urwid<2.2.0
Requires-Dist: packaging
Dynamic: license-file
